cache_manager/__init__.py
cache_manager/base.py
cache_manager/etcd.py
cache_manager/memcached.py
cache_manager/pickle.py
cache_manager/redis.py
cache_manager-0.1.dist-info/METADATA
cache_manager-0.1.dist-info/WHEEL
cache_manager-0.1.dist-info/top_level.txt
cache_manager-0.1.dist-info/RECORD
