Metadata-Version: 2.1
Name: cache-manager
Version: 0.1
Summary: Simple cache manager
Home-page: https://github.com/alex19pov31/cache-manager
Author: Alexander Nesterov
Author-email: alex19pov31@gmail.com
License: MIT
Platform: UNKNOWN
